xarray_plotly/__init__.py
xarray_plotly/accessor.py
xarray_plotly/common.py
xarray_plotly/config.py
xarray_plotly/plotting.py
xarray_plotly/py.typed
xarray_plotly-0.0.6.dist-info/licenses/LICENSE
xarray_plotly-0.0.6.dist-info/METADATA
xarray_plotly-0.0.6.dist-info/WHEEL
xarray_plotly-0.0.6.dist-info/top_level.txt
xarray_plotly-0.0.6.dist-info/RECORD
