Metadata-Version: 2.4
Name: xarray_plotly
Version: 0.0.6
Summary: Interactive Plotly Express plotting accessor for xarray
Author: Felix
License: MIT
Project-URL: Homepage, https://github.com/FBumann/xarray_plotly
Project-URL: Documentation, https://fbumann.github.io/xarray_plotly
Project-URL: Repository, https://github.com/FBumann/xarray_plotly
Keywords: xarray,plotly,visualization,interactive,plotting
Classifier: Development Status :: 3 - Alpha
Classifier: Intended Audience :: Science/Research
Classifier: License :: OSI Approved :: MIT License
Classifier: Operating System :: OS Independent
Classifier: Programming Language :: Python :: 3
Classifier: Programming Language :: Python :: 3.10
Classifier: Programming Language :: Python :: 3.11
Classifier: Programming Language :: Python :: 3.12
Classifier: Programming Language :: Python :: 3.13
Classifier: Topic :: Scientific/Engineering :: Visualization
Requires-Python: >=3.10
License-File: LICENSE
Requires-Dist: xarray>=2023.1.0
Requires-Dist: plotly>=5.0.0
Requires-Dist: pandas>=1.5.0
Provides-Extra: dev
Requires-Dist: pytest==9.0.2; extra == "dev"
Requires-Dist: pytest-cov==7.0.0; extra == "dev"
Requires-Dist: mypy==1.19.1; extra == "dev"
Requires-Dist: ruff==0.14.11; extra == "dev"
Requires-Dist: pre-commit==4.5.1; extra == "dev"
Requires-Dist: nbstripout==0.8.2; extra == "dev"
Provides-Extra: docs
Requires-Dist: mkdocs==1.6.1; extra == "docs"
Requires-Dist: mkdocs-material==9.7.1; extra == "docs"
Requires-Dist: mkdocstrings[python]==1.0.0; extra == "docs"
Requires-Dist: mkdocs-jupyter==0.25.1; extra == "docs"
Requires-Dist: mkdocs-plotly-plugin==0.1.3; extra == "docs"
Requires-Dist: jupyter==1.1.1; extra == "docs"
Dynamic: license-file
